PixPayloadGen
