Metadata-Version: 2.1
Name: PixPayloadGen
Version: 0.0.5
Summary: Gerar Payload pix com QRCODE
Author: REIZINHODEV
Author-email: edleyteixeira@hotmail.com
License: MIT License
Keywords: pix payload gerar
License-File: LICENSE
